moveread/pipelines/annotation/__init__.py
moveread/pipelines/annotation/__init__.pyi
moveread/pipelines/annotation/_api.py
moveread/pipelines/annotation/cli.py
moveread/pipelines/annotation/clientgen_cli.py
moveread/pipelines/annotation/sdk.py
moveread/pipelines/annotation/spec.py
moveread/pipelines/annotation/preprocessed/__init__.py
moveread/pipelines/annotation/preprocessed/__init__.pyi
moveread/pipelines/annotation/preprocessed/cli.py
moveread/pipelines/annotation/preprocessed/local.py
moveread/pipelines/annotation/preprocessed/spec.py
moveread/pipelines/annotation/preprocessed/core_io/__init__.py
moveread/pipelines/annotation/preprocessed/core_io/__init__.pyi
moveread/pipelines/annotation/preprocessed/core_io/core.py
moveread_pipelines_annotation-0.1.7.dist-info/METADATA
moveread_pipelines_annotation-0.1.7.dist-info/WHEEL
moveread_pipelines_annotation-0.1.7.dist-info/entry_points.txt
moveread_pipelines_annotation-0.1.7.dist-info/top_level.txt
moveread_pipelines_annotation-0.1.7.dist-info/RECORD
